csmmix/__init__.py
csmmix/mix.py
csmmix-1.0.1.dist-info/LICENSE
csmmix-1.0.1.dist-info/METADATA
csmmix-1.0.1.dist-info/WHEEL
csmmix-1.0.1.dist-info/top_level.txt
csmmix-1.0.1.dist-info/RECORD
